Metadata-Version: 2.1
Name: cfn-man
Version: 0.0.1
Summary: man pages for cloud formation
Home-page: UNKNOWN
Author: Steven Miller
Author-email: sjmiller609@gmail.com
License: UNKNOWN
Platform: UNKNOWN
Classifier: Programming Language :: Python :: 2
Classifier: License :: OSI Approved :: MIT License
Classifier: Operating System :: Unix
